{
    "title": "Chinese Culture 3 @ SAP California",
    "questions": [
        {
            "text": "Which holiday does NOT relate to family?",
            "answers": [
                { "id": "A", "text": "Spring Festival" },
                { "id": "B", "text": "Mid-autumn Festival" },
                { "id": "C", "text": "National Holiday" },
                { "id": "D", "text": "Tomb-Sweeping Day" }
            ],
            "rightAnswerId": "C"
        },
        {
            "text": "Which social app is most popular in China?",
            "answers": [
                { "id": "A", "text": "Instagram" },
                { "id": "B", "text": "Wechat" },
                { "id": "C", "text": "Facebook" },
                { "id": "D", "text": "Weibo" }
            ],
            "rightAnswerId": "B"
        },
        {
            "text": "Which two mobile payment apps are most popular in China?",
            "answers": [
                { "id": "A", "text": "Wechat and Unionpay" },
                { "id": "B", "text": "Wechat and Apple Pay" },
                { "id": "C", "text": "Wechat and Alipay" },
                { "id": "D", "text": "Wechat and Paypal" }
            ],
            "rightAnswerId": "C"
        },
        {
            "text": "Which river can be called the Mother River of China?",
            "answers": [
                { "id": "A", "text": "Yangtze River" },
                { "id": "B", "text": "Yellow River" },
                { "id": "C", "text": "Nile River" },
                { "id": "D", "text": "Amazon river" }
            ],
            "rightAnswerId": "B"
        },
        {
            "text": "Which ocean is next to China?",
            "answers": [
                { "id": "A", "text": "The Atlantic Ocean" },
                { "id": "B", "text": "The Indian Ocean" },
                { "id": "C", "text": "The Pacific Ocean" },
                { "id": "D", "text": "The Arctic Ocean" }
            ],
            "rightAnswerId": "C"
        },
        {
            "text": "How many stars are on the national flag of China?",
            "answers": [
                { "id": "A", "text": "6" },
                { "id": "B", "text": "8" },
                { "id": "C", "text": "3" },
                { "id": "D", "text": "5" }
            ],
            "rightAnswerId": "D"
        } 
    ]
}